{
  "5": {
    "inputs": {
      "width": 1024,
      "height": 576,
      "batch_size": 1
    },
    "class_type": "EmptyLatentImage",
    "_meta": {
      "title": "空Latent图像"
    }
  },
  "6": {
    "inputs": {
      "text": "**Scene Description:**\n\nThe scene opens in a vibrant, sunlit backyard, filled with lush green grass and colorful flowers. The sky is a warm, clear blue, with a few fluffy white clouds drifting lazily by. The environment is filled with the playful energy of a perfect day for outdoor games.\n\nIn the center of the frame stands a young Asian girl, around 8 years old, with expressive, slightly exaggerated features that capture her excitement and joy. She has short, dark hair tied up in two small pigtails, and she's wearing a bright, cheerful yellow dress with a floral pattern. Her eyes are wide with anticipation, and her cheeks are rosy, reflecting her enthusiasm.\n\nThe girl is standing with one foot slightly forward, as if she’s about to take off running. She has one hand held up to her mouth, as if she’s just finished speaking, and the other hand is pointing playfully at a nearby bush, suggesting where someone might hide. Her body language is full of energy and movement, conveying her eagerness to start the game of hide-and-seek.\n\nBehind her, a large, friendly-looking tree with a tire swing hangs from one of its branches, adding to the playful atmosphere. The tire swing is gently swaying in the breeze, creating a sense of motion and life. A small, colorful wooden fence borders the yard, and a few toys, like a ball and a toy car, are scattered around, adding to the lived-in, child-friendly feel of the space.\n\nIn the background, a cozy, well-kept house with a red door and white shutters can be seen, providing a sense of safety and home. The windows are open, and a light curtain flutters in the breeze, adding to the natural, airy feel of the scene.\n\nThe camera angle is slightly low, looking up at the girl, which emphasizes her importance and the joy of the moment. The lighting is soft and warm, with a gentle, natural depth of field that keeps the focus on the girl while still allowing the viewer to appreciate the charming, detailed environment around her.\n\nOverall, the scene is a delightful, heartwarming depiction of a child’s imagination and the simple, joyful moments of childhood, perfectly capturing the playful and engaging tone of the conversation.",
      "clip": [
        "11",
        0
      ]
    },
    "class_type": "CLIPTextEncode",
    "_meta": {
      "title": "CLIP文本编码"
    }
  },
  "8": {
    "inputs": {
      "samples": [
        "13",
        0
      ],
      "vae": [
        "10",
        0
      ]
    },
    "class_type": "VAEDecode",
    "_meta": {
      "title": "VAE解码"
    }
  },
  "9": {
    "inputs": {
      "images": [
        "8",
        0
      ]
    },
    "class_type": "SaveImageWebsocket",
    "_meta": {
      "title": "通过WebSocket保存图像"
    }
  },
  "19": {
    "inputs": {
      "filename_prefix": "api_1782489896_54bde7ca",
      "images": [
        "8",
        0
      ]
    },
    "class_type": "SaveImage",
    "_meta": {
      "title": "保存图像到磁盘"
    }
  },
  "10": {
    "inputs": {
      "vae_name": "ae.safetensors"
    },
    "class_type": "VAELoader",
    "_meta": {
      "title": "加载VAE"
    }
  },
  "11": {
    "inputs": {
      "clip_name1": "t5xxl_fp16.safetensors",
      "clip_name2": "clip_l.safetensors",
      "type": "flux",
      "device": "default"
    },
    "class_type": "DualCLIPLoader",
    "_meta": {
      "title": "双CLIP加载器"
    }
  },
  "12": {
    "inputs": {
      "unet_name": "flux1-schnell.safetensors",
      "weight_dtype": "default"
    },
    "class_type": "UNETLoader",
    "_meta": {
      "title": "UNet加载器"
    }
  },
  "13": {
    "inputs": {
      "noise": [
        "25",
        0
      ],
      "guider": [
        "22",
        0
      ],
      "sampler": [
        "16",
        0
      ],
      "sigmas": [
        "17",
        0
      ],
      "latent_image": [
        "5",
        0
      ]
    },
    "class_type": "SamplerCustomAdvanced",
    "_meta": {
      "title": "自定义采样器（高级）"
    }
  },
  "16": {
    "inputs": {
      "sampler_name": "euler"
    },
    "class_type": "KSamplerSelect",
    "_meta": {
      "title": "K采样器选择"
    }
  },
  "17": {
    "inputs": {
      "scheduler": "simple",
      "steps": 4,
      "denoise": 1.0,
      "model": [
        "12",
        0
      ]
    },
    "class_type": "BasicScheduler",
    "_meta": {
      "title": "基本调度器"
    }
  },
  "22": {
    "inputs": {
      "model": [
        "12",
        0
      ],
      "conditioning": [
        "6",
        0
      ]
    },
    "class_type": "BasicGuider",
    "_meta": {
      "title": "基本引导器"
    }
  },
  "25": {
    "inputs": {
      "noise_seed": 854958927192159
    },
    "class_type": "RandomNoise",
    "_meta": {
      "title": "随机噪波"
    }
  }
}