{
  "1": {
    "class_type": "UNETLoader",
    "inputs": {
      "unet_name": "flux1-dev.safetensors",
      "weight_dtype": "default"
    }
  },
  "2": {
    "class_type": "DualCLIPLoader",
    "inputs": {
      "clip_name1": "clip_l.safetensors",
      "clip_name2": "t5xxl_fp16.safetensors",
      "type": "flux"
    }
  },
  "3": {
    "class_type": "VAELoader",
    "inputs": {
      "vae_name": "ae.safetensors"
    }
  },
  "4": {
    "class_type": "CLIPTextEncode",
    "inputs": {
      "clip": [
        "2",
        0
      ],
      "text": "A young Korean woman with dark brown wavy shoulder-length hair stands in profile view, framed through a mossy stone archway on a foggy forest trail at dawn. Shot on 35mm lens, environmental portrait. Soft window-like diffused morning light creates a Rembrandt triangle shadow across her delicate features and button nose. She wears a school uniform inspired preppy look — navy blazer, pleated skirt, knee socks, loosened tie. Her expression is elegant and sophisticated, chin slightly lifted, gazing into the mist. Dewy flawless skin, subtle gradient lip tint, soft brown eyeshadow. Wisps of fog curl around her silhouette. Shallow depth of field, muted earth tones, ethereal atmosphere. Photorealistic, editorial fashion photography, no text, no watermarks."
    }
  },
  "5": {
    "class_type": "FluxGuidance",
    "inputs": {
      "conditioning": [
        "4",
        0
      ],
      "guidance": 3.5
    }
  },
  "6": {
    "class_type": "CLIPTextEncode",
    "inputs": {
      "clip": [
        "2",
        0
      ],
      "text": ""
    }
  },
  "7": {
    "class_type": "EmptySD3LatentImage",
    "inputs": {
      "width": 1024,
      "height": 1024,
      "batch_size": 1
    }
  },
  "8": {
    "class_type": "KSampler",
    "inputs": {
      "model": [
        "1",
        0
      ],
      "positive": [
        "5",
        0
      ],
      "negative": [
        "6",
        0
      ],
      "latent_image": [
        "7",
        0
      ],
      "seed": 1910717982,
      "control_after_generate": "fixed",
      "steps": 20,
      "cfg": 1.0,
      "sampler_name": "euler",
      "scheduler": "simple",
      "denoise": 1.0
    }
  },
  "9": {
    "class_type": "VAEDecode",
    "inputs": {
      "samples": [
        "8",
        0
      ],
      "vae": [
        "3",
        0
      ]
    }
  },
  "10": {
    "class_type": "SaveImage",
    "inputs": {
      "images": [
        "9",
        0
      ],
      "filename_prefix": "portrait_1910717982"
    }
  }
}