{
  "1": {
    "class_type": "UNETLoader",
    "inputs": {
      "unet_name": "flux1-dev.safetensors",
      "weight_dtype": "default"
    }
  },
  "2": {
    "class_type": "DualCLIPLoader",
    "inputs": {
      "clip_name1": "clip_l.safetensors",
      "clip_name2": "t5xxl_fp16.safetensors",
      "type": "flux"
    }
  },
  "3": {
    "class_type": "VAELoader",
    "inputs": {
      "vae_name": "ae.safetensors"
    }
  },
  "4": {
    "class_type": "LoraLoaderModelOnly",
    "inputs": {
      "model": [
        "1",
        0
      ],
      "lora_name": "flux_korean_girl.safetensors",
      "strength_model": 0.8
    }
  },
  "5": {
    "class_type": "CLIPTextEncode",
    "inputs": {
      "clip": [
        "2",
        0
      ],
      "text": "Extreme close-up portrait of a stunning Korean idol woman with ash brown braided half-up hairstyle, sharp jawline and mesmerizing cat-like eyes with dreamy ethereal expression. Profile view side angle, half body waist up, wearing an elegant evening gown with shimmering sequins catching light. Standing on a subway platform with trains creating motion blur streaks behind her. Golden hour warm side light casting amber glow across flawless porcelain skin, highlighting every pore and lash in macro lens detail. Shallow depth of field isolating her against the urban rush. Styled dewy makeup with glass-skin finish, soft coral lips slightly parted. Ethereal atmosphere with warm bokeh from platform lights. Hyper detailed skin texture, photorealistic, editorial fashion photography."
    }
  },
  "6": {
    "class_type": "FluxGuidance",
    "inputs": {
      "conditioning": [
        "5",
        0
      ],
      "guidance": 3.5
    }
  },
  "7": {
    "class_type": "CLIPTextEncode",
    "inputs": {
      "clip": [
        "2",
        0
      ],
      "text": ""
    }
  },
  "8": {
    "class_type": "EmptySD3LatentImage",
    "inputs": {
      "width": 1024,
      "height": 1024,
      "batch_size": 1
    }
  },
  "9": {
    "class_type": "KSampler",
    "inputs": {
      "model": [
        "4",
        0
      ],
      "positive": [
        "6",
        0
      ],
      "negative": [
        "7",
        0
      ],
      "latent_image": [
        "8",
        0
      ],
      "seed": 634145719,
      "control_after_generate": "fixed",
      "steps": 24,
      "cfg": 1.0,
      "sampler_name": "euler",
      "scheduler": "simple",
      "denoise": 1.0
    }
  },
  "10": {
    "class_type": "VAEDecode",
    "inputs": {
      "samples": [
        "9",
        0
      ],
      "vae": [
        "3",
        0
      ]
    }
  },
  "11": {
    "class_type": "SaveImage",
    "inputs": {
      "images": [
        "10",
        0
      ],
      "filename_prefix": "portrait_634145719"
    }
  }
}