{
  "5": {
    "inputs": {
      "width": 1024,
      "height": 576,
      "batch_size": 1
    },
    "class_type": "EmptyLatentImage",
    "_meta": {
      "title": "空Latent图像"
    }
  },
  "6": {
    "inputs": {
      "text": "**Scene Description:**\n\n**Visual Style:**\n- The scene is rendered in a vibrant, Pixar-style 3D animation with warm, inviting colors. The lighting is soft and natural, casting gentle shadows that add depth and warmth to the environment. The characters have slightly exaggerated, expressive features that convey their emotions clearly.\n\n**Composition:**\n- The scene shows a young Asian girl, **Nian Nian**, standing in a cozy, well-lit room. She is wearing a cute, colorful dress with a playful pattern, and her hair is tied up in two neat pigtails. Her full body is visible from head to toe.\n- The room is decorated with elements that reflect a child's imagination and comfort. There are soft, plush toys scattered on the floor, a small, cozy bed with a colorful quilt, and a window with a view of a serene, starry night sky.\n- Nian Nian is interacting with a large, friendly-looking stuffed bear, which she is hugging tightly. The bear is as tall as she is, and it has a warm, comforting expression.\n\n**Environment:**\n- The background includes a wooden bookshelf filled with colorful books, a small desk with crayons and drawing paper, and a few framed pictures on the walls. The room is tidy but lived-in, with a sense of warmth and familiarity.\n- A small, round table with a lamp casts a soft, warm glow, adding to the cozy atmosphere. The window is slightly open, allowing a gentle breeze to flow in, making the curtains flutter softly.\n\n**Visual Effects:**\n- The camera angle is low, looking up at Nian Nian, emphasizing her perspective and the importance of the moment. The shot is framed to highlight her interaction with the bear, with the rest of the room in the background.\n- The lighting is soft and ambient, with a warm, golden hue that enhances the emotional tone of the scene. The depth of field is used to keep Nian Nian and the bear in sharp focus, while the background is slightly blurred, drawing attention to the main subjects.\n- The overall composition is balanced, with the elements of the room arranged in a way that feels natural and lived-in, yet still visually appealing and engaging.\n\n**Emotional Tone:**\n- Nian Nian's face is a mix of slight concern and comfort, as she hugs the bear. Her eyes are wide and expressive, showing a hint of worry, but also a sense of security and trust. The bear's presence is a source of comfort, and this is reflected in her relaxed posture and the gentle smile on her face.\n- The scene captures the heart of the conversation, where Nian Nian is expressing her feelings and seeking reassurance. The bear, as a symbol of comfort and companionship, provides a visual representation of the care and support she is receiving.\n\n**Final Image:**\n- The final image is a beautifully composed, emotionally resonant scene that captures the essence of the conversation. It is playful, clear, and full of warmth, reflecting the child's imaginative and heartfelt response. The setting and characters are grounded in a clear, imaginative, and visually compelling environment, making the scene both relatable and enchanting.",
      "clip": [
        "11",
        0
      ]
    },
    "class_type": "CLIPTextEncode",
    "_meta": {
      "title": "CLIP文本编码"
    }
  },
  "8": {
    "inputs": {
      "samples": [
        "13",
        0
      ],
      "vae": [
        "10",
        0
      ]
    },
    "class_type": "VAEDecode",
    "_meta": {
      "title": "VAE解码"
    }
  },
  "9": {
    "inputs": {
      "images": [
        "8",
        0
      ]
    },
    "class_type": "SaveImageWebsocket",
    "_meta": {
      "title": "通过WebSocket保存图像"
    }
  },
  "19": {
    "inputs": {
      "filename_prefix": "api_1781387601_869560f0",
      "images": [
        "8",
        0
      ]
    },
    "class_type": "SaveImage",
    "_meta": {
      "title": "保存图像到磁盘"
    }
  },
  "10": {
    "inputs": {
      "vae_name": "ae.safetensors"
    },
    "class_type": "VAELoader",
    "_meta": {
      "title": "加载VAE"
    }
  },
  "11": {
    "inputs": {
      "clip_name1": "t5xxl_fp16.safetensors",
      "clip_name2": "clip_l.safetensors",
      "type": "flux",
      "device": "default"
    },
    "class_type": "DualCLIPLoader",
    "_meta": {
      "title": "双CLIP加载器"
    }
  },
  "12": {
    "inputs": {
      "unet_name": "flux1-schnell.safetensors",
      "weight_dtype": "default"
    },
    "class_type": "UNETLoader",
    "_meta": {
      "title": "UNet加载器"
    }
  },
  "13": {
    "inputs": {
      "noise": [
        "25",
        0
      ],
      "guider": [
        "22",
        0
      ],
      "sampler": [
        "16",
        0
      ],
      "sigmas": [
        "17",
        0
      ],
      "latent_image": [
        "5",
        0
      ]
    },
    "class_type": "SamplerCustomAdvanced",
    "_meta": {
      "title": "自定义采样器（高级）"
    }
  },
  "16": {
    "inputs": {
      "sampler_name": "euler"
    },
    "class_type": "KSamplerSelect",
    "_meta": {
      "title": "K采样器选择"
    }
  },
  "17": {
    "inputs": {
      "scheduler": "simple",
      "steps": 4,
      "denoise": 1.0,
      "model": [
        "12",
        0
      ]
    },
    "class_type": "BasicScheduler",
    "_meta": {
      "title": "基本调度器"
    }
  },
  "22": {
    "inputs": {
      "model": [
        "12",
        0
      ],
      "conditioning": [
        "6",
        0
      ]
    },
    "class_type": "BasicGuider",
    "_meta": {
      "title": "基本引导器"
    }
  },
  "25": {
    "inputs": {
      "noise_seed": 854958927192159
    },
    "class_type": "RandomNoise",
    "_meta": {
      "title": "随机噪波"
    }
  }
}