{
  "3": {
    "inputs": {
      "seed": 31,
      "steps": 8,
      "cfg": 1.0,
      "sampler_name": "euler",
      "scheduler": "simple",
      "denoise": 1.0,
      "model": [
        "78",
        0
      ],
      "positive": [
        "94",
        0
      ],
      "negative": [
        "47",
        0
      ],
      "latent_image": [
        "98",
        0
      ]
    },
    "class_type": "KSampler",
    "_meta": {
      "title": "K采样器"
    }
  },
  "18": {
    "inputs": {
      "samples": [
        "3",
        0
      ],
      "vae": [
        "97",
        2
      ]
    },
    "class_type": "VAEDecodeAudio",
    "_meta": {
      "title": "VAE解码（音频）"
    }
  },
  "47": {
    "inputs": {
      "conditioning": [
        "94",
        0
      ]
    },
    "class_type": "ConditioningZeroOut",
    "_meta": {
      "title": "条件零化"
    }
  },
  "78": {
    "inputs": {
      "shift": 3.0,
      "model": [
        "97",
        0
      ]
    },
    "class_type": "ModelSamplingAuraFlow",
    "_meta": {
      "title": "采样算法（AuraFlow）"
    }
  },
  "94": {
    "inputs": {
      "tags": "这是一首伤感压抑的情歌，情绪层次丰富。开篇是甜蜜热烈的爱恋，彼此许下真挚诺言；紧接着慢慢发现层层谎言，温情之下全是伪装；随后陷入无休止的猜忌与争吵，美好假象彻底破碎；最终两个人潦草走散。整首歌结尾，主人公反复复盘过往相处的细节，才看清这段感情从头到尾布满虚伪，满心失望与唏嘘。",
      "lyrics": "【Intro 前奏】\n（温柔低缓钢琴，轻微氛围底噪）\n【Verse 1 主歌 1】\n最初温柔 伪装得太完美\n满眼热忱 骗我坠入暧昧\n情话温柔 句句都像珍贵\n我义无反顾 掏尽真心奉陪\n慢慢发觉 温柔藏着虚伪\n热烈氛围 只是一时暧昧\n太多敷衍 藏在沉默细微\n所有心动 不过是一场虚伪点缀\n【Chorus 副歌】\n看清爱恋里 所有虚假与狼狈\n甜蜜是铺垫 最后只剩崩溃落泪\n炙热的相拥 全是刻意的虚伪\n深情的过往 全是演好的对位\n从温柔沉醉 走到失望的颓废\n所有的真心 败给虚假的暧昧\n爱过一场后 终于彻底领会\n最伤人的爱 从来都藏着虚伪\n【Verse 2 主歌 2】\n无数争吵 撕开所有完美\n温柔假面 碎得支离破碎\n所谓偏爱 从来不曾纯粹\n我执着过往 困在谎言轮回\n热烈褪去 只剩敷衍疲惫\n所有承诺 全都随风作废\n认真的我 输得太过绝对\n原来爱情本质 皆是虚假虚伪\n【Chorus 副歌】\n看清爱恋里 所有虚假与狼狈\n甜蜜是铺垫 最后只剩崩溃落泪\n炙热的相拥 全是刻意的虚伪\n深情的过往 全是演好的对位\n从温柔沉醉 走到失望的颓废\n所有的真心 败给虚假的暧昧\n爱过一场后 终于彻底领会\n最伤人的爱 从来都藏着虚伪\n【Bridge 桥段】\n我反复回想 相处所有细节\n才看懂所有温柔都是演技\n那些心动 那些朝夕\n全是虚假剧本 骗我入戏\n真心终究 抵不过虚伪假意\n炙热过往 只剩遗憾堆积\n耗尽热忱 彻底清醒\n爱情最真的真相 是谎言藏底\n【Chorus 副歌（升调加厚）】\n看清爱恋里 所有虚假与狼狈\n甜蜜是铺垫 最后只剩崩溃落泪\n炙热的相拥 全是刻意的虚伪\n深情的过往 全是演好的对位\n从温柔沉醉 走到失望的颓废\n所有的真心 败给虚假的暧昧\n爱过一场后 终于彻底领会\n最伤人的爱 从来都藏着虚伪\n【Outro 尾奏】\n（渐弱、温柔留白）\n所有温柔…… 皆是虚伪\n所有热爱…… 终成作废",
      "seed": 31,
      "bpm": 105,
      "duration": 240.0,
      "timesignature": "2",
      "language": "zh",
      "keyscale": "D minor",
      "generate_audio_codes": true,
      "cfg_scale": 2.0,
      "temperature": 0.85,
      "top_p": 0.9,
      "top_k": 0,
      "min_p": 0.0,
      "clip": [
        "97",
        1
      ]
    },
    "class_type": "TextEncodeAceStepAudio1.5",
    "_meta": {
      "title": "TextEncodeAceStepAudio1.5"
    }
  },
  "97": {
    "inputs": {
      "ckpt_name": "Ace_Step_1.5\\ace_step_1.5_turbo_aio.safetensors"
    },
    "class_type": "CheckpointLoaderSimple",
    "_meta": {
      "title": "Checkpoint加载器（简易）"
    }
  },
  "98": {
    "inputs": {
      "seconds": 240.0,
      "batch_size": 1
    },
    "class_type": "EmptyAceStep1.5LatentAudio",
    "_meta": {
      "title": "Empty Ace Step 1.5 Latent Audio"
    }
  },
  "104": {
    "inputs": {
      "filename_prefix": "audio/ace-step-1.5",
      "quality": "128k",
      "audioUI": "",
      "audio": [
        "18",
        0
      ]
    },
    "class_type": "SaveAudioMP3",
    "_meta": {
      "title": "保存音频 (MP3)"
    }
  }
}