{
  "4": {
    "inputs": {
      "ckpt_name": "CHEYENNE_v16.safetensors"
    },
    "class_type": "CheckpointLoaderSimple",
    "_meta": {
      "title": "Load Checkpoint"
    }
  },
  "6": {
    "inputs": {
      "text": [
        "113",
        0
      ],
      "clip": [
        "4",
        1
      ]
    },
    "class_type": "CLIPTextEncode",
    "_meta": {
      "title": "CLIP Text Encode (Prompt)"
    }
  },
  "7": {
    "inputs": {
      "text": "2d, photo, nsfw, paintings, worst quality, low quality, normal quality, lowres, watermark, monochrome, grayscale, ugly, blurry, bad anatomy, morbid, malformation, amputation, bad proportions, missing body, fused body, extra head, poorly drawn face, bad eyes, deformed eye, unclear eyes, cross-eyed, long neck, malformed limbs, extra limbs, extra arms, missing arms, bad tongue, strange fingers, mutated hands, missing hands, poorly drawn hands, extra hands, fused hands, connected hand, bad hands, wrong fingers, missing fingers, extra fingers, 4 fingers, 3 fingers, deformed hands, extra legs, bad legs, many legs, more than two legs, bad feet, wrong feet, extra feets,",
      "clip": [
        "4",
        1
      ]
    },
    "class_type": "CLIPTextEncode",
    "_meta": {
      "title": "CLIP Text Encode (Prompt)"
    }
  },
  "8": {
    "inputs": {
      "samples": [
        "120",
        0
      ],
      "vae": [
        "4",
        2
      ]
    },
    "class_type": "VAEDecode",
    "_meta": {
      "title": "VAE Decode"
    }
  },
  "11": {
    "inputs": {
      "pixels": [
        "12",
        0
      ],
      "vae": [
        "4",
        2
      ]
    },
    "class_type": "VAEEncode",
    "_meta": {
      "title": "VAE Encode"
    }
  },
  "12": {
    "inputs": {
      "image": "Temp_1782171210230.jpeg"
    },
    "class_type": "LoadImage",
    "_meta": {
      "title": "Load Image"
    }
  },
  "112": {
    "inputs": {
      "text": ", (masterpiece),(highest quality),Anime,(extremely detailed),figurine, best quality,4K,super detail,"
    },
    "class_type": "CR Text",
    "_meta": {
      "title": "🔤 CR Text"
    }
  },
  "113": {
    "inputs": {
      "text_1": "",
      "text_2": [
        "112",
        0
      ]
    },
    "class_type": "ConcatText_Zho",
    "_meta": {
      "title": "✨ConcatText_Zho"
    }
  },
  "117": {
    "inputs": {
      "hard_mode": true,
      "boost": true,
      "model": [
        "4",
        0
      ]
    },
    "class_type": "Automatic CFG",
    "_meta": {
      "title": "Automatic CFG"
    }
  },
  "118": {
    "inputs": {
      "ckpt_name": "depth_anything_vitl14.pth",
      "resolution": 512,
      "image": [
        "12",
        0
      ]
    },
    "class_type": "DepthAnythingPreprocessor",
    "_meta": {
      "title": "Depth Anything"
    }
  },
  "119": {
    "inputs": {
      "model_type": "SDXL",
      "steps": 12,
      "denoise": 0.8
    },
    "class_type": "AlignYourStepsScheduler",
    "_meta": {
      "title": "AlignYourStepsScheduler"
    }
  },
  "120": {
    "inputs": {
      "add_noise": true,
      "noise_seed": 286314587675700,
      "cfg": 6.5,
      "model": [
        "117",
        0
      ],
      "positive": [
        "205",
        0
      ],
      "negative": [
        "205",
        1
      ],
      "sampler": [
        "121",
        0
      ],
      "sigmas": [
        "119",
        0
      ],
      "latent_image": [
        "11",
        0
      ]
    },
    "class_type": "SamplerCustom",
    "_meta": {
      "title": "SamplerCustom"
    }
  },
  "121": {
    "inputs": {
      "sampler_name": "dpmpp_2m"
    },
    "class_type": "KSamplerSelect",
    "_meta": {
      "title": "KSamplerSelect"
    }
  },
  "178": {
    "inputs": {
      "merge_with_lineart": "lineart_standard",
      "resolution": 512,
      "lineart_lower_bound": 0.0,
      "lineart_upper_bound": 1.0,
      "object_min_size": 36,
      "object_connectivity": 1,
      "image": [
        "12",
        0
      ]
    },
    "class_type": "AnyLineArtPreprocessor_aux",
    "_meta": {
      "title": "AnyLine Lineart"
    }
  },
  "204": {
    "inputs": {
      "strength": 0.8,
      "start_percent": 0.0,
      "end_percent": 0.8,
      "positive": [
        "6",
        0
      ],
      "negative": [
        "7",
        0
      ],
      "control_net": [
        "206",
        0
      ],
      "image": [
        "118",
        0
      ]
    },
    "class_type": "ControlNetApplyAdvanced",
    "_meta": {
      "title": "Apply ControlNet"
    }
  },
  "205": {
    "inputs": {
      "strength": 0.6,
      "start_percent": 0.0,
      "end_percent": 0.6,
      "positive": [
        "204",
        0
      ],
      "negative": [
        "204",
        1
      ],
      "control_net": [
        "207",
        0
      ],
      "image": [
        "178",
        0
      ]
    },
    "class_type": "ControlNetApplyAdvanced",
    "_meta": {
      "title": "Apply ControlNet"
    }
  },
  "206": {
    "inputs": {
      "control_net_name": "control-lora-depth-rank256.safetensors"
    },
    "class_type": "ControlNetLoader",
    "_meta": {
      "title": "Load ControlNet Model"
    }
  },
  "207": {
    "inputs": {
      "control_net_name": "control-lora-sketch-rank256.safetensors"
    },
    "class_type": "ControlNetLoader",
    "_meta": {
      "title": "Load ControlNet Model"
    }
  },
  "208": {
    "inputs": {
      "filename_prefix": "ComfyUI",
      "images": [
        "211",
        0
      ]
    },
    "class_type": "SaveImage",
    "_meta": {
      "title": "Save Image"
    }
  },
  "211": {
    "inputs": {
      "score": 0.7000000000000001,
      "image": [
        "8",
        0
      ],
      "alternative_image": [
        "212",
        0
      ]
    },
    "class_type": "NSFWDetection",
    "_meta": {
      "title": "NSFWDetection"
    }
  },
  "212": {
    "inputs": {
      "width": 512,
      "height": 512,
      "red": 255,
      "green": 255,
      "blue": 255
    },
    "class_type": "Image Blank",
    "_meta": {
      "title": "Image Blank"
    }
  }
}